march_agent/__init__.py
march_agent/agent.py
march_agent/agent_state_client.py
march_agent/app.py
march_agent/artifact.py
march_agent/attachment_client.py
march_agent/checkpoint_client.py
march_agent/checkpointer.py
march_agent/cli.py
march_agent/conversation.py
march_agent/conversation_client.py
march_agent/conversation_message.py
march_agent/exceptions.py
march_agent/gateway_client.py
march_agent/gateway_pb2.py
march_agent/gateway_pb2_grpc.py
march_agent/heartbeat.py
march_agent/loki_handler.py
march_agent/memory.py
march_agent/memory_client.py
march_agent/message.py
march_agent/py.typed
march_agent/streamer.py
march_agent/extensions/__init__.py
march_agent/extensions/langgraph.py
march_agent/extensions/pydantic_ai.py
march_agent/structural/__init__.py
march_agent/structural/artifact.py
march_agent/structural/base.py
march_agent/structural/stepper.py
march_agent/structural/surface.py
march_agent/structural/text_block.py
march_agent-0.3.1.dist-info/licenses/LICENSE
march_agent-0.3.1.dist-info/METADATA
march_agent-0.3.1.dist-info/WHEEL
march_agent-0.3.1.dist-info/entry_points.txt
march_agent-0.3.1.dist-info/top_level.txt
march_agent-0.3.1.dist-info/RECORD
