Metadata-Version: 2.4
Name: march-agent
Version: 0.3.1
Summary: Python SDK for March AI Agent framework - handles agent registration, message consumption, and streaming responses
Author-email: March AI <support@march.ai>
License: MIT
Project-URL: Homepage, https://github.com/march-us/march-agent
Project-URL: Repository, https://github.com/march-us/march-agent
Project-URL: Documentation, https://github.com/march-us/march-agent#readme
Classifier: Development Status :: 4 - Beta
Classifier: Intended Audience :: Developers
Classifier: License :: OSI Approved :: MIT License
Classifier: Programming Language :: Python :: 3
Classifier: Programming Language :: Python :: 3.10
Classifier: Programming Language :: Python :: 3.11
Classifier: Programming Language :: Python :: 3.12
Classifier: Topic :: Software Development :: Libraries :: Python Modules
Requires-Python: >=3.10
License-File: LICENSE
Requires-Dist: grpcio>=1.70.0
Requires-Dist: grpcio-tools>=1.70.0
Requires-Dist: protobuf>=5.29.0
Requires-Dist: requests>=2.31.0
Requires-Dist: aiohttp>=3.9.0
Provides-Extra: dev
Requires-Dist: pytest>=7.4.0; extra == "dev"
Requires-Dist: pytest-asyncio>=0.21.0; extra == "dev"
Requires-Dist: pytest-cov>=4.1.0; extra == "dev"
Requires-Dist: pytest-mock>=3.11.0; extra == "dev"
Requires-Dist: respx>=0.20.0; extra == "dev"
Provides-Extra: langgraph
Requires-Dist: langgraph>=1.0.0; extra == "langgraph"
Requires-Dist: langchain-core>=0.3.0; extra == "langgraph"
Provides-Extra: pydantic
Requires-Dist: pydantic-ai>=1.0.0; extra == "pydantic"
Dynamic: license-file
